[
  {
    "firstName": " Janet",
    "lastName": "Bewley",
    "image": "http://docs.legis.wisconsin.gov/2017/legislators/senate/1500.jpg",
    "website": "http://legis.wisconsin.gov/senate/25/bewley",
    "party": "(D - Ashland)",
    "district": "District 25",
    "capitolAddress": "Room 126 SouthState CapitolMadison, WI 53707-7882",
    "phoneOne": "(608) 266-3510",
    "phoneTwo": "(800) 469-6562",
    "email": "Sen.Bewley@legis.wi.gov",
    "votingAddress": "60995 Pike River RoadMason, WI 54856",
    "staff": "Geoff.Gaston@legis.wisconsin.gov | Joseph.Hoey@legis.wisconsin.gov | Eric.LaGesse@legis.wisconsin.gov | Lori.Youngman@legis.wisconsin.gov"
  },
  {
    "firstName": " Tim",
    "lastName": "Carpenter",
    "image": "http://docs.legis.wisconsin.gov/2017/legislators/senate/1501.jpg",
    "website": "http://legis.wisconsin.gov/senate/carpenter/",
    "party": "(D - Milwaukee)",
    "district": "District 3",
    "capitolAddress": "Room 109 SouthState CapitolMadison, WI 53707-7882",
    "phoneOne": "(608) 266-8535",
    "phoneTwo": "",
    "email": "Sen.Carpenter@legis.wisconsin.gov",
    "votingAddress": "2957 South 38th StreetMilwaukee, WI  53215",
    "staff": "Russell.DeLong@legis.wisconsin.gov | stuart.ewy@legis.wisconsin.gov | Scott.May@legis.wisconsin.gov"
  },
  {
    "firstName": " Robert",
    "lastName": "Cowles",
    "image": "http://docs.legis.wisconsin.gov/2017/legislators/senate/1502.jpg",
    "website": "http://legis.wisconsin.gov/senate/cowles/",
    "party": "(R - Green Bay)",
    "district": "District 2",
    "capitolAddress": "Room 118 SouthState CapitolMadison, WI 53707-7882",
    "phoneOne": "(608) 266-0484",
    "phoneTwo": "(800) 334-1465",
    "email": "Sen.Cowles@legis.wisconsin.gov",
    "votingAddress": "300 W. St. Joseph StreetUnit 23, Green Bay, WI  54301",
    "staff": "Toni.Herkert@legis.wisconsin.gov | Evan.Miller@legis.wisconsin.gov | Heather.Moore@legis.wisconsin.gov | Jason.Mugnaini@legis.wisconsin.gov"
  },
  {
    "firstName": " David",
    "lastName": "Craig",
    "image": "http://docs.legis.wisconsin.gov/2017/legislators/senate/1646.jpg",
    "website": "/2017/legislators/senate/1646",
    "party": "(R - Big Bend)",
    "district": "District 28",
    "capitolAddress": "Room 104 SouthState CapitolMadison, WI 53708",
    "phoneOne": "(608) 266-5400",
    "phoneTwo": "",
    "email": "Sen.Craig@legis.wisconsin.gov",
    "votingAddress": "P.O. Box 323Big Bend, WI 53103",
    "staff": "Adam.Gibbs@legis.wisconsin.gov | Sam.Hope@legis.wisconsin.gov | William.Neville@legis.wisconsin.gov | Chad.Taylor@legis.wisconsin.gov"
  },
  {
    "firstName": " Alberta",
    "lastName": "Darling",
    "image": "http://docs.legis.wisconsin.gov/2017/legislators/senate/1503.jpg",
    "website": "http://legis.wisconsin.gov/senate/darling/",
    "party": "(R - River Hills)",
    "district": "District 8",
    "capitolAddress": "Room 317 EastState CapitolMadison, WI 53707-7882",
    "phoneOne": "(608) 266-5830",
    "phoneTwo": "",
    "email": "Sen.Darling@legis.wisconsin.gov",
    "votingAddress": "1325 West Dean RoadRiver Hills, WI 53217",
    "staff": "Bob.Delaporte@legis.wisconsin.gov | Cory.Fish@legis.wisconsin.gov | Rachel.Keith@legis.wisconsin.gov | RJ.Lambert@legis.wisconsin.gov | Deej.Lundgren@legis.wisconsin.gov | Jerry.Ponio@legis.wisconsin.gov"
  },
  {
    "firstName": " Jon",
    "lastName": "Erpenbach",
    "image": "http://docs.legis.wisconsin.gov/2017/legislators/senate/1504.jpg",
    "website": "http://legis.wisconsin.gov/senate/erpenbach/",
    "party": "(D - Middleton)",
    "district": "District 27",
    "capitolAddress": "Room 7 SouthState CapitolMadison, WI 53707-7882",
    "phoneOne": "(608) 266-6670",
    "phoneTwo": "",
    "email": "Sen.Erpenbach@legis.wisconsin.gov",
    "votingAddress": "2316 Clark StreetMiddleton, WI  53562",
    "staff": "Kelly.Becker@legis.wisconsin.gov | Tryg.Knutson@legis.wisconsin.gov | Julie.Laundrie@legis.wisconsin.gov | Amanda.Tomten@legis.wisconsin.gov"
  },
  {
    "firstName": " Dan",
    "lastName": "Feyen",
    "image": "http://docs.legis.wisconsin.gov/2017/legislators/senate/1644.jpg",
    "website": "http://legis.wisconsin.gov/senate/18/feyen",
    "party": "",
    "district": "District 18",
    "capitolAddress": "Room 306 SouthState CapitolMadison, WI 53707-7882",
    "phoneOne": "(608) 266-5300",
    "phoneTwo": "",
    "email": "Sen.Feyen@legis.wi.gov",
    "votingAddress": "Fond du Lac, WI 54936",
    "staff": "Rohn.Bishop@legis.wisconsin.gov | Marie.Jolly@legis.wisconsin.gov | Tim.Lakin@legis.wisconsin.gov | Gregory.Quella@legis.wisconsin.gov"
  },
  {
    "firstName": " Scott",
    "lastName": "Fitzgerald",
    "image": "http://docs.legis.wisconsin.gov/2017/legislators/senate/1505.jpg",
    "website": "http://legis.wisconsin.gov/senate/13/fitzgerald/",
    "party": "(R - Juneau)",
    "district": "District 13",
    "capitolAddress": "Room 211 SouthState CapitolMadison, WI 53707-7882",
    "phoneOne": "(608) 266-5660",
    "phoneTwo": "",
    "email": "Sen.Fitzgerald@legis.wisconsin.gov",
    "votingAddress": "N4692 Maple RoadJuneau, WI  53039",
    "staff": "Cindy.Block@legis.wisconsin.gov | Adam.Foltz@legis.wisconsin.gov | Kimber.Liedl@legis.wisconsin.gov | Tad.Ottman@legis.wisconsin.gov | Dan.Romportl@legis.wisconsin.gov | Myranda.Tanck@legis.wisconsin.gov"
  },
  {
    "firstName": " Dave",
    "lastName": "Hansen",
    "image": "http://docs.legis.wisconsin.gov/2017/legislators/senate/1507.jpg",
    "website": "http://legis.wisconsin.gov/senate/hansen/",
    "party": "(D - Green Bay)",
    "district": "District 30",
    "capitolAddress": "Room 106 SouthState CapitolMadison, WI 53707-7882",
    "phoneOne": "(608) 266-5670",
    "phoneTwo": "",
    "email": "Sen.Hansen@legis.wisconsin.gov",
    "votingAddress": "3489 Blackwolf RunGreen Bay, WI  54311",
    "staff": "jessica.lundquist@legis.wisconsin.gov | Jay.Wadd@legis.wisconsin.gov | John.Wagnitz@legis.wisconsin.gov"
  },
  {
    "firstName": " Sheila",
    "lastName": "Harsdorf",
    "image": "http://docs.legis.wisconsin.gov/2017/legislators/senate/1509.jpg",
    "website": "http://legis.wisconsin.gov/senate/harsdorf/",
    "party": "(R - River Falls)",
    "district": "District 10",
    "capitolAddress": "Room 122 SouthState CapitolMadison, WI 53707-7882",
    "phoneOne": "(608) 266-7745",
    "phoneTwo": "",
    "email": "Sen.Harsdorf@legis.wisconsin.gov",
    "votingAddress": "N6627 County Road E.River Falls, WI  54022",
    "staff": "Kim.Drake@legis.wisconsin.gov | Brooke.Froelich@legis.wisconsin.gov | Terri.Griffiths@legis.wisconsin.gov | Holly.Walker@legis.wisconsin.gov"
  },
  {
    "firstName": " LaTonya",
    "lastName": "Johnson",
    "image": "http://docs.legis.wisconsin.gov/2017/legislators/senate/1643.jpg",
    "website": "/2017/legislators/senate/1643",
    "party": "(D - Milwaukee)",
    "district": "District 6",
    "capitolAddress": "Room 22 SouthState CapitolMadison, WI 53708",
    "phoneOne": "(608) 266-2500",
    "phoneTwo": "",
    "email": "Sen.Johnson@legis.wisconsin.gov",
    "votingAddress": "2363 N. 54th St.Milwaukee, WI  53210",
    "staff": "Frederic.Ludwig@legis.wisconsin.gov | Shannon.McCoy@legis.wisconsin.gov | Christian.Ullsvik@legis.wisconsin.gov"
  },
  {
    "firstName": " Chris",
    "lastName": "Kapenga",
    "image": "http://docs.legis.wisconsin.gov/2017/legislators/senate/1510.jpg",
    "website": "http://legis.wisconsin.gov/senate/33/kapenga",
    "party": "(R - Delafield)",
    "district": "District 33",
    "capitolAddress": "Room 15 SouthState CapitolMadison, WI 53707-7882",
    "phoneOne": "(608) 266-9174",
    "phoneTwo": "(800) 863-8883",
    "email": "Sen.Kapenga@legis.wisconsin.gov",
    "votingAddress": "N9W31035 Concord Ct.Delafield, WI 53018",
    "staff": "Caleb.Gerbitz@legis.wisconsin.gov | Kyle.Koenen@legis.wisconsin.gov | Jeff.Sherman@legis.wisconsin.gov | Kaleb.VanderWiele@legis.wisconsin.gov"
  },
  {
    "firstName": " Chris",
    "lastName": "Larson",
    "image": "http://docs.legis.wisconsin.gov/2017/legislators/senate/1511.jpg",
    "website": "http://legis.wisconsin.gov/senate/07/Larson",
    "party": "(D - Milwaukee)",
    "district": "District 7",
    "capitolAddress": "Room 20 SouthState CapitolMadison, WI 53707-7882",
    "phoneOne": "(608) 266-7505",
    "phoneTwo": "(800) 361-5487",
    "email": "Sen.Larson@legis.wisconsin.gov",
    "votingAddress": "3261 S. Herman StreetMilwaukee, WI  53207",
    "staff": "Lacy.Fox@legis.wisconsin.gov | Nick.Janis@legis.wisconsin.gov | Justin.Sargent@legis.wisconsin.gov"
  },
  {
    "firstName": " Frank",
    "lastName": "Lasee",
    "image": "http://docs.legis.wisconsin.gov/2017/legislators/senate/1512.jpg",
    "website": "http://legis.wisconsin.gov/senate/lasee/",
    "party": "(R - De Pere)",
    "district": "District 1",
    "capitolAddress": "Room 316 SouthState CapitolMadison, WI 53707-7882",
    "phoneOne": "(608) 266-3512",
    "phoneTwo": "",
    "email": "Sen.Lasee@legis.wisconsin.gov",
    "votingAddress": "De Pere, WI 54115",
    "staff": "Lars.Fiorio@legis.wisconsin.gov | Robert.Kovach@legis.wisconsin.gov | Tricia.Sieg@legis.wisconsin.gov"
  },
  {
    "firstName": " Devin",
    "lastName": "LeMahieu",
    "image": "http://docs.legis.wisconsin.gov/2017/legislators/senate/1515.jpg",
    "website": "http://legis.wisconsin.gov/senate/09/LeMahieu",
    "party": "(R - Oostburg)",
    "district": "District 9",
    "capitolAddress": "Room 323 SouthState CapitolMadison, WI 53707-7882",
    "phoneOne": "(608) 266-2056",
    "phoneTwo": "",
    "email": "Sen.LeMahieu@legis.wisconsin.gov",
    "votingAddress": "21 S 8th StreetOostburg, WI 53070",
    "staff": "Darryl.Carlson@legis.wisconsin.gov | Ashley.Czaja@legis.wisconsin.gov | Luke.Petrovich@legis.wisconsin.gov | Craig.Summerfield@legis.wisconsin.gov"
  },
  {
    "firstName": " Howard",
    "lastName": "Marklein",
    "image": "http://docs.legis.wisconsin.gov/2017/legislators/senate/1516.jpg",
    "website": "http://legis.wisconsin.gov/senate/17/marklein",
    "party": "(R - Spring Green)",
    "district": "District 17",
    "capitolAddress": "Room 8 SouthState CapitolMadison, WI 53707-7882",
    "phoneOne": "(608) 266-0703",
    "phoneTwo": "",
    "email": "Sen.Marklein@legis.wi.gov",
    "votingAddress": "S11665 Soeldner RoadSpring Green, WI 53588",
    "staff": "Scott.Coenen@legis.wisconsin.gov | Katy.Prange@legis.wisconsin.gov | Matthew.Rainey@legis.wisconsin.gov | Vincent.Williams@legis.wisconsin.gov"
  },
  {
    "firstName": " Mark",
    "lastName": "Miller",
    "image": "http://docs.legis.wisconsin.gov/2017/legislators/senate/1517.jpg",
    "website": "http://legis.wisconsin.gov/senate/miller/",
    "party": "(D - Monona)",
    "district": "District 16",
    "capitolAddress": "Room 19 SouthState CapitolMadison, WI 53707-7882",
    "phoneOne": "(608) 266-9170",
    "phoneTwo": "",
    "email": "Sen.Miller@legis.wisconsin.gov",
    "votingAddress": "4903 Roigan TerraceMonona, WI  53716",
    "staff": "john.anderson@legis.wisconsin.gov | Beth.Bier@legis.wisconsin.gov | Sam.Erickson@legis.wisconsin.gov | Bridget.Esser@legis.wisconsin.gov"
  },
  {
    "firstName": " Terry",
    "lastName": "Moulton",
    "image": "http://docs.legis.wisconsin.gov/2017/legislators/senate/1518.jpg",
    "website": "http://legis.wisconsin.gov/senate/moulton/",
    "party": "(R - Chippewa Falls)",
    "district": "District 23",
    "capitolAddress": "Room 310 SouthState CapitolMadison, WI 53707-7882",
    "phoneOne": "(608) 266-7511",
    "phoneTwo": "",
    "email": "Sen.Moulton@legis.wisconsin.gov",
    "votingAddress": "980 118th StreetChippewa Falls, WI  54729",
    "staff": "Nathan.Duerkop@legis.wisconsin.gov | Scott.Nelson@legis.wisconsin.gov | Mikayla.Olsen@legis.wisconsin.gov | Zachary.Stollfus@legis.wisconsin.gov"
  },
  {
    "firstName": " Stephen",
    "lastName": "Nass",
    "image": "http://docs.legis.wisconsin.gov/2017/legislators/senate/1519.jpg",
    "website": "http://legis.wisconsin.gov/senate/11/nass",
    "party": "(R - Whitewater)",
    "district": "District 11",
    "capitolAddress": "Room 10 SouthState CapitolMadison, WI 53707-7882",
    "phoneOne": "(608) 266-2635",
    "phoneTwo": "",
    "email": "Sen.Nass@legis.wisconsin.gov",
    "votingAddress": "N8330 Jackson Road,Whitewater, WI   53190",
    "staff": "Adam.Field@legis.wisconsin.gov | Mike.Mikalsen@legis.wisconsin.gov | Michael.Murphy@legis.wisconsin.gov"
  },
  {
    "firstName": " Luther",
    "lastName": "Olsen",
    "image": "http://docs.legis.wisconsin.gov/2017/legislators/senate/1520.jpg",
    "website": "http://legis.wisconsin.gov/senate/olsen/",
    "party": "(R - Ripon)",
    "district": "District 14",
    "capitolAddress": "Room 313 SouthState CapitolMadison, WI 53707-7882",
    "phoneOne": "(608) 266-0751",
    "phoneTwo": "",
    "email": "Sen.Olsen@legis.wisconsin.gov",
    "votingAddress": "1023 Thomas StreetRipon, WI  54971",
    "staff": "Shelby.Lemke@legis.wisconsin.gov | Mary.Pluta@legis.wisconsin.gov | Dustin.Truax@legis.wisconsin.gov | Jenna.Zantow@legis.wisconsin.gov"
  },
  {
    "firstName": " Jerry",
    "lastName": "Petrowski",
    "image": "http://docs.legis.wisconsin.gov/2017/legislators/senate/1521.jpg",
    "website": "http://legis.wisconsin.gov/senate/petrowski",
    "party": "(R - Marathon)",
    "district": "District 29",
    "capitolAddress": "Room 123 SouthState CapitolMadison, WI 53707-7882",
    "phoneOne": "(608) 266-2502",
    "phoneTwo": "",
    "email": "Sen.Petrowski@legis.wisconsin.gov",
    "votingAddress": "720 North 136th AvenueMarathon, WI   54448",
    "staff": "Lindsey.Brabender@legis.wisconsin.gov | Tim.Fiocchi@legis.wisconsin.gov | Kelsey.Kleist@legis.wisconsin.gov | Derek.Punches@legis.wisconsin.gov"
  },
  {
    "firstName": " Janis",
    "lastName": "Ringhand",
    "image": "http://docs.legis.wisconsin.gov/2017/legislators/senate/1522.jpg",
    "website": "http://legis.wisconsin.gov/senate/15/ringhand",
    "party": "(D - Evansville)",
    "district": "District 15",
    "capitolAddress": "Room 3 SouthState CapitolMadison, WI 53707-7882",
    "phoneOne": "(608) 266-2253",
    "phoneTwo": "",
    "email": "Sen.Ringhand@legis.wi.gov",
    "votingAddress": "412 Fowler Cir.,Evansville, WI 53536",
    "staff": "James.Macken@legis.wisconsin.gov | Jim.Smith@legis.wisconsin.gov | Patrick.Walsh@legis.wisconsin.gov"
  },
  {
    "firstName": " Fred",
    "lastName": "Risser",
    "image": "http://docs.legis.wisconsin.gov/2017/legislators/senate/1523.jpg",
    "website": "http://legis.wisconsin.gov/senate/risser",
    "party": "(D - Madison)",
    "district": "District 26",
    "capitolAddress": "Room 130 SouthState CapitolMadison, WI 53707-7882",
    "phoneOne": "(608) 266-1627",
    "phoneTwo": "",
    "email": "Sen.Risser@legis.wisconsin.gov",
    "votingAddress": "100 Wisconsin Avenue, Unit 501Madison, WI 53703",
    "staff": "Cassie.Jurenci@legis.wisconsin.gov | Kara.Sailing@legis.wisconsin.gov | Terry.Tuschen@legis.wisconsin.gov"
  },
  {
    "firstName": " Roger",
    "lastName": "Roth",
    "image": "http://docs.legis.wisconsin.gov/2017/legislators/senate/1524.jpg",
    "website": "/2017/legislators/senate/1524",
    "party": "(R - Appleton)",
    "district": "District 19",
    "capitolAddress": "Room 220 SouthState CapitolMadison, WI 53707-7882",
    "phoneOne": "(608) 266-0718",
    "phoneTwo": "(800) 579-8717",
    "email": "Sen.Roth@legis.wisconsin.gov",
    "votingAddress": "1910 W Charles StreetAppleton, WI 54914",
    "staff": "Daniel.Dubnicka@legis.wisconsin.gov | Matt.Henkel@legis.wisconsin.gov | Bill.Kloiber@legis.wisconsin.gov | Jason.Vick@legis.wisconsin.gov"
  },
  {
    "firstName": " Jennifer",
    "lastName": "Shilling",
    "image": "http://docs.legis.wisconsin.gov/2017/legislators/senate/1525.jpg",
    "website": "http://legis.wisconsin.gov/senate/shilling/",
    "party": "(D - La Crosse)",
    "district": "District 32",
    "capitolAddress": "Room 206 SouthState CapitolMadison, WI 53707-7882",
    "phoneOne": "(608) 266-5490",
    "phoneTwo": "",
    "email": "Sen.Shilling@legis.wisconsin.gov",
    "votingAddress": "2608 Main StreetLa Crosse, WI  54601",
    "staff": "Kate.Constalie@legis.wisconsin.gov | Taylor.Goodine@legis.wisconsin.gov | Katherine.Iliff@legis.wisconsin.gov | Tony.Palese@legis.wisconsin.gov | Kara.Pennoyer@legis.wisconsin.gov | Danielle.Williams@legis.wisconsin.gov | Steven.Worley@legis.wisconsin.gov"
  },
  {
    "firstName": " Duey",
    "lastName": "Stroebel",
    "image": "http://docs.legis.wisconsin.gov/2017/legislators/senate/1526.jpg",
    "website": "http://legis.wisconsin.gov/senate/20/stroebel",
    "party": "(R - Saukville)",
    "district": "District 20",
    "capitolAddress": "Room 18 SouthState CapitolMadison, WI 53707-7882",
    "phoneOne": "(608) 266-7513",
    "phoneTwo": "",
    "email": "Sen.Stroebel@legis.wisconsin.gov",
    "votingAddress": "2428 Covered Bridge RoadSaukville, WI  53080",
    "staff": "Ethan.Hollenberger@legis.wisconsin.gov | Nick.Schiltz@legis.wisconsin.gov | Brian.Sikma@legis.wisconsin.gov | John.Soper@legis.wisconsin.gov"
  },
  {
    "firstName": " Lena",
    "lastName": "Taylor",
    "image": "http://docs.legis.wisconsin.gov/2017/legislators/senate/1527.jpg",
    "website": "http://legis.wisconsin.gov/senate/04/taylor",
    "party": "(D - Milwaukee)",
    "district": "District 4",
    "capitolAddress": "Room 5 SouthState CapitolMadison, WI 53707-7882",
    "phoneOne": "(608) 266-5810",
    "phoneTwo": "",
    "email": "Sen.Taylor@legis.wisconsin.gov",
    "votingAddress": "1518 West CapitolMilwaukee, 53206",
    "staff": "Ladette.Austin@legis.wisconsin.gov | Jessica.FordKelly@legis.wisconsin.gov | Greg.Packnett@legis.wisconsin.gov | Donna.Shepard@legis.wisconsin.gov | Craig.Trost@legis.wisconsin.gov"
  },
  {
    "firstName": " Patrick",
    "lastName": "Testin",
    "image": "http://docs.legis.wisconsin.gov/2017/legislators/senate/1645.jpg",
    "website": "/2017/legislators/senate/1645",
    "party": "",
    "district": "District 24",
    "capitolAddress": "Room 131 SouthState CapitolMadison, WI 53707-7882",
    "phoneOne": "(608) 266-3123",
    "phoneTwo": "",
    "email": "Sen.Testin@legis.wi.gov",
    "votingAddress": "5369 Fairview DriveStevens Point, WI 54482",
    "staff": "Natalie.Aicher@legis.wisconsin.gov | James.Emerson@legis.wisconsin.gov | Jeff.Schultz@legis.wisconsin.gov | Matt.Spencer@legis.wisconsin.gov"
  },
  {
    "firstName": " Thomas",
    "lastName": "Tiffany",
    "image": "http://docs.legis.wisconsin.gov/2017/legislators/senate/1528.jpg",
    "website": "http://legis.wisconsin.gov/senate/12/tiffany",
    "party": "(R - Hazelhurst)",
    "district": "District 12",
    "capitolAddress": "Room 409 SouthState CapitolMadison, WI 53707-7882",
    "phoneOne": "(608) 266-2509",
    "phoneTwo": "",
    "email": "Sen.Tiffany@legis.wi.gov",
    "votingAddress": "4973 Willow Dam Rd.Hazelhurst, WI 54531",
    "staff": "Dominic.Belmonte@legis.wisconsin.gov | Timothy.Duffy@legis.wisconsin.gov | Mitchel.Ohly@legis.wisconsin.gov | Tyler.Wenzlaff@legis.wisconsin.gov"
  },
  {
    "firstName": " Kathleen",
    "lastName": "Vinehout",
    "image": "http://docs.legis.wisconsin.gov/2017/legislators/senate/1529.jpg",
    "website": "http://legis.wisconsin.gov/senate/vinehout",
    "party": "(D - Alma)",
    "district": "District 31",
    "capitolAddress": "Room 108 SouthState CapitolMadison, WI 53707-7882",
    "phoneOne": "(608) 266-8546",
    "phoneTwo": "(877) 763-6636",
    "email": "Sen.Vinehout@legis.wisconsin.gov",
    "votingAddress": "W1490 Cesler Valley RoadAlma, WI  54610",
    "staff": "Linda.Kleinschmidt@legis.wisconsin.gov | Beau.Stafford@legis.wisconsin.gov | Jacob.Wipperfurth@legis.wisconsin.gov"
  },
  {
    "firstName": " Leah",
    "lastName": "Vukmir",
    "image": "http://docs.legis.wisconsin.gov/2017/legislators/senate/1530.jpg",
    "website": "http://legis.wisconsin.gov/senate/vukmir",
    "party": "(R - Brookfield)",
    "district": "District 5",
    "capitolAddress": "Room 415 SouthState CapitolMadison, WI 53707-7882",
    "phoneOne": "(608) 266-2512",
    "phoneTwo": "",
    "email": "Sen.Vukmir@legis.wisconsin.gov",
    "votingAddress": "945 Post RoadBrookfield, WI  53005",
    "staff": "Jason.Booth@legis.wisconsin.gov | Mattias.Gugel@legis.wisconsin.gov | Ben.Nesvold@legis.wisconsin.gov | Jessica.Ward@legis.wisconsin.gov"
  },
  {
    "firstName": " Van",
    "lastName": "Wanggaard",
    "image": "http://docs.legis.wisconsin.gov/2017/legislators/senate/1531.jpg",
    "website": "http://legis.wisconsin.gov/senate/21/wanggaard",
    "party": "(R - Racine)",
    "district": "District 21",
    "capitolAddress": "Room 319 SouthState CapitolMadison, WI 53707-7882",
    "phoneOne": "(608) 266-1832",
    "phoneTwo": "(866) 615-7510",
    "email": "Sen.Wanggaard@legis.wisconsin.gov",
    "votingAddress": "1246 Blaine Avenue,Racine, WI  53405",
    "staff": "Scott.Kelly@legis.wisconsin.gov | Valirie.Maxim@legis.wisconsin.gov | Colleen.Moran@legis.wisconsin.gov | Michelle.Osdene@legis.wisconsin.gov"
  },
  {
    "firstName": " Robert",
    "lastName": "Wirch",
    "image": "http://docs.legis.wisconsin.gov/2017/legislators/senate/1532.jpg",
    "website": "http://legis.wisconsin.gov/senate/wirch",
    "party": "(D - Kenosha)",
    "district": "District 22",
    "capitolAddress": "Room 127 SouthState CapitolMadison, WI 53707-7882",
    "phoneOne": "(608) 267-8979",
    "phoneTwo": "",
    "email": "Sen.Wirch@legis.wisconsin.gov",
    "votingAddress": "Kenosha, WI 53144",
    "staff": "Steven.Gillitzer@legis.wisconsin.gov | Paula.McGuire@legis.wisconsin.gov | Stephen.Pienkos@legis.wisconsin.gov"
  }
]
